easyenergy/__init__.py
easyenergy/const.py
easyenergy/easyenergy.py
easyenergy/exceptions.py
easyenergy/models.py
easyenergy/py.typed
easyenergy-2.2.0.dist-info/LICENSE
easyenergy-2.2.0.dist-info/METADATA
easyenergy-2.2.0.dist-info/WHEEL
easyenergy-2.2.0.dist-info/RECORD
